pyboxd/__init__.py
pyboxd/film.py
pyboxd/lists.py
pyboxd/pyboxd.py
pyboxd/user.py
pyboxd-0.1.0.dist-info/AUTHORS.rst
pyboxd-0.1.0.dist-info/LICENSE
pyboxd-0.1.0.dist-info/METADATA
pyboxd-0.1.0.dist-info/WHEEL
pyboxd-0.1.0.dist-info/top_level.txt
pyboxd-0.1.0.dist-info/RECORD
