Metadata-Version: 2.1
Name: pyboxd
Version: 0.1.0
Summary: A Python Letterboxd webscraping Library with BeautifulSoup and requests.
Home-page: https://github.com/yourusername/pyboxd
Author: Juan Fernandez Cruz
Author-email: Juan Antonio Fernandez Cruz <fercruzjuan2002@gmail.com>
Maintainer-email: Juan Antonio Fernandez Cruz <fercruzjuan2002@gmail.com>
License: MIT license
Project-URL: bugs, https://github.com/juanjuanjuanfer/pyboxd/issues
Project-URL: changelog, https://github.com/juanjuanjuanfer/pyboxd/blob/master/changelog.md
Project-URL: homepage, https://github.com/juanjuanjuanfer/pyboxd
Requires-Python: >=3.6
License-File: LICENSE
License-File: AUTHORS.rst
Provides-Extra: dev
Requires-Dist: coverage; extra == "dev"
Requires-Dist: mypy; extra == "dev"
Requires-Dist: pytest; extra == "dev"
Requires-Dist: ruff; extra == "dev"
